<?xml version="1.0"?>
<program>
    <first>A</first>
    <fin>Y</fin>
    <rule>
        <initcondition>
            <state>KR</state>
            <symbol>R</symbol>
        </initcondition>
        <action>
            <state>TR</state>
            <symbol>R</symbol>
            <move>RIGHT</move>
        </action>
    </rule>
    <rule>
        <initcondition>
            <state>KL</state>
            <symbol>1</symbol>
        </initcondition>
        <action>
            <state>ML</state>
            <symbol>O</symbol>
            <move>LEFT</move>
        </action>
    </rule>
    <rule>
        <initcondition>
            <state>TR0</state>
            <symbol>c</symbol>
        </initcondition>
        <action>
            <state>TR0</state>
            <symbol>c</symbol>
            <move>RIGHT</move>
        </action>
    </rule>
    <rule>
        <initcondition>
            <state>ML</state>
            <symbol>C</symbol>
        </initcondition>
        <action>
            <state>NL</state>
            <symbol>c</symbol>
            <move>RIGHT</move>
        </action>
    </rule>
    <rule>
        <initcondition>
            <state>TL0</state>
            <symbol>c</symbol>
        </initcondition>
        <action>
            <state>TL0</state>
            <symbol>c</symbol>
            <move>RIGHT</move>
        </action>
    </rule>
    <rule>
        <initcondition>
            <state>E</state>
            <symbol>c</symbol>
        </initcondition>
        <action>
            <state>F</state>
            <symbol>c</symbol>
            <move>LEFT</move>
        </action>
    </rule>
    <rule>
        <initcondition>
            <state>F</state>
            <symbol>0</symbol>
        </initcondition>
        <action>
            <state>E</state>
            <symbol>0</symbol>
            <move>LEFT</move>
        </action>
    </rule>
    <rule>
        <initcondition>
            <state>ML</state>
            <symbol>L</symbol>
        </initcondition>
        <action>
            <state>ML</state>
            <symbol>L</symbol>
            <move>LEFT</move>
        </action>
    </rule>
    <rule>
        <initcondition>
            <state>TR</state>
            <symbol>0</symbol>
        </initcondition>
        <action>
            <state>TR0</state>
            <symbol>0</symbol>
            <move>RIGHT</move>
        </action>
    </rule>
    <rule>
        <initcondition>
            <state>TR</state>
            <symbol>1</symbol>
        </initcondition>
        <action>
            <state>TR1</state>
            <symbol>1</symbol>
            <move>RIGHT</move>
        </action>
    </rule>
    <rule>
        <initcondition>
            <state>F</state>
            <symbol>1</symbol>
        </initcondition>
        <action>
            <state>E</state>
            <symbol>1</symbol>
            <move>LEFT</move>
        </action>
    </rule>
    <rule>
        <initcondition>
            <state>B</state>
            <symbol>c</symbol>
        </initcondition>
        <action>
            <state>B</state>
            <symbol>c</symbol>
            <move>RIGHT</move>
        </action>
    </rule>
    <rule>
        <initcondition>
            <state>PL</state>
            <symbol>0</symbol>
        </initcondition>
        <action>
            <state>NL</state>
            <symbol>0</symbol>
            <move>RIGHT</move>
        </action>
    </rule>
    <rule>
        <initcondition>
            <state>C0</state>
            <symbol>c</symbol>
        </initcondition>
        <action>
            <state>C0</state>
            <symbol>c</symbol>
            <move>LEFT</move>
        </action>
    </rule>
    <rule>
        <initcondition>
            <state>X6</state>
            <symbol>0</symbol>
        </initcondition>
        <action>
            <state>Y</state>
            <symbol>0</symbol>
            <move>RIGHT</move>
        </action>
    </rule>
    <rule>
        <initcondition>
            <state>TR0</state>
            <symbol>R</symbol>
        </initcondition>
        <action>
            <state>TR0</state>
            <symbol>R</symbol>
            <move>RIGHT</move>
        </action>
    </rule>
    <rule>
        <initcondition>
            <state>ML</state>
            <symbol>R</symbol>
        </initcondition>
        <action>
            <state>ML</state>
            <symbol>R</symbol>
            <move>LEFT</move>
        </action>
    </rule>
    <rule>
        <initcondition>
            <state>TR0</state>
            <symbol>O</symbol>
        </initcondition>
        <action>
            <state>U</state>
            <symbol>0</symbol>
            <move>RIGHT</move>
        </action>
    </rule>
    <rule>
        <initcondition>
            <state>TR0</state>
            <symbol>N</symbol>
        </initcondition>
        <action>
            <state>U</state>
            <symbol>0</symbol>
            <move>RIGHT</move>
        </action>
    </rule>
    <rule>
        <initcondition>
            <state>TR0</state>
            <symbol>L</symbol>
        </initcondition>
        <action>
            <state>TR0</state>
            <symbol>L</symbol>
            <move>RIGHT</move>
        </action>
    </rule>
    <rule>
        <initcondition>
            <state>C1</state>
            <symbol>L</symbol>
        </initcondition>
        <action>
            <state>C1</state>
            <symbol>L</symbol>
            <move>LEFT</move>
        </action>
    </rule>
    <rule>
        <initcondition>
            <state>TL1</state>
            <symbol>1</symbol>
        </initcondition>
        <action>
            <state>TL1</state>
            <symbol>1</symbol>
            <move>RIGHT</move>
        </action>
    </rule>
    <rule>
        <initcondition>
            <state>KL</state>
            <symbol>R</symbol>
        </initcondition>
        <action>
            <state>TR</state>
            <symbol>R</symbol>
            <move>RIGHT</move>
        </action>
    </rule>
    <rule>
        <initcondition>
            <state>TL1</state>
            <symbol>0</symbol>
        </initcondition>
        <action>
            <state>TL1</state>
            <symbol>0</symbol>
            <move>RIGHT</move>
        </action>
    </rule>
    <rule>
        <initcondition>
            <state>J</state>
            <symbol>0</symbol>
        </initcondition>
        <action>
            <state>J</state>
            <symbol>0</symbol>
            <move>RIGHT</move>
        </action>
    </rule>
    <rule>
        <initcondition>
            <state>KL</state>
            <symbol>L</symbol>
        </initcondition>
        <action>
            <state>TL</state>
            <symbol>L</symbol>
            <move>RIGHT</move>
        </action>
    </rule>
    <rule>
        <initcondition>
            <state>KR</state>
            <symbol>1</symbol>
        </initcondition>
        <action>
            <state>MR</state>
            <symbol>O</symbol>
            <move>RIGHT</move>
        </action>
    </rule>
    <rule>
        <initcondition>
            <state>U</state>
            <symbol>0</symbol>
        </initcondition>
        <action>
            <state>C0</state>
            <symbol>N</symbol>
            <move>LEFT</move>
        </action>
    </rule>
    <rule>
        <initcondition>
            <state>U</state>
            <symbol>1</symbol>
        </initcondition>
        <action>
            <state>C1</state>
            <symbol>O</symbol>
            <move>LEFT</move>
        </action>
    </rule>
    <rule>
        <initcondition>
            <state>J</state>
            <symbol>1</symbol>
        </initcondition>
        <action>
            <state>J</state>
            <symbol>1</symbol>
            <move>RIGHT</move>
        </action>
    </rule>
    <rule>
        <initcondition>
            <state>B</state>
            <symbol>R</symbol>
        </initcondition>
        <action>
            <state>B</state>
            <symbol>R</symbol>
            <move>RIGHT</move>
        </action>
    </rule>
    <rule>
        <initcondition>
            <state>ML</state>
            <symbol>c</symbol>
        </initcondition>
        <action>
            <state>ML</state>
            <symbol>c</symbol>
            <move>LEFT</move>
        </action>
    </rule>
    <rule>
        <initcondition>
            <state>C1</state>
            <symbol>C</symbol>
        </initcondition>
        <action>
            <state>D1</state>
            <symbol>c</symbol>
            <move>RIGHT</move>
        </action>
    </rule>
    <rule>
        <initcondition>
            <state>B</state>
            <symbol>O</symbol>
        </initcondition>
        <action>
            <state>C1</state>
            <symbol>O</symbol>
            <move>LEFT</move>
        </action>
    </rule>
    <rule>
        <initcondition>
            <state>B</state>
            <symbol>N</symbol>
        </initcondition>
        <action>
            <state>C0</state>
            <symbol>N</symbol>
            <move>LEFT</move>
        </action>
    </rule>
    <rule>
        <initcondition>
            <state>B</state>
            <symbol>L</symbol>
        </initcondition>
        <action>
            <state>B</state>
            <symbol>L</symbol>
            <move>RIGHT</move>
        </action>
    </rule>
    <rule>
        <initcondition>
            <state>TL1</state>
            <symbol>B</symbol>
        </initcondition>
        <action>
            <state>U</state>
            <symbol>1</symbol>
            <move>LEFT</move>
        </action>
    </rule>
    <rule>
        <initcondition>
            <state>F</state>
            <symbol>R</symbol>
        </initcondition>
        <action>
            <state>E</state>
            <symbol>R</symbol>
            <move>LEFT</move>
        </action>
    </rule>
    <rule>
        <initcondition>
            <state>TL1</state>
            <symbol>C</symbol>
        </initcondition>
        <action>
            <state>TL1</state>
            <symbol>C</symbol>
            <move>RIGHT</move>
        </action>
    </rule>
    <rule>
        <initcondition>
            <state>TR1</state>
            <symbol>1</symbol>
        </initcondition>
        <action>
            <state>TR1</state>
            <symbol>1</symbol>
            <move>RIGHT</move>
        </action>
    </rule>
    <rule>
        <initcondition>
            <state>TR1</state>
            <symbol>0</symbol>
        </initcondition>
        <action>
            <state>TR1</state>
            <symbol>0</symbol>
            <move>RIGHT</move>
        </action>
    </rule>
    <rule>
        <initcondition>
            <state>TL</state>
            <symbol>0</symbol>
        </initcondition>
        <action>
            <state>TL0</state>
            <symbol>0</symbol>
            <move>RIGHT</move>
        </action>
    </rule>
    <rule>
        <initcondition>
            <state>TL</state>
            <symbol>1</symbol>
        </initcondition>
        <action>
            <state>TL1</state>
            <symbol>1</symbol>
            <move>RIGHT</move>
        </action>
    </rule>
    <rule>
        <initcondition>
            <state>B</state>
            <symbol>B</symbol>
        </initcondition>
        <action>
            <state>CB</state>
            <symbol>B</symbol>
            <move>LEFT</move>
        </action>
    </rule>
    <rule>
        <initcondition>
            <state>KR</state>
            <symbol>L</symbol>
        </initcondition>
        <action>
            <state>TL</state>
            <symbol>L</symbol>
            <move>RIGHT</move>
        </action>
    </rule>
    <rule>
        <initcondition>
            <state>X2</state>
            <symbol>0</symbol>
        </initcondition>
        <action>
            <state>X3</state>
            <symbol>0</symbol>
            <move>RIGHT</move>
        </action>
    </rule>
    <rule>
        <initcondition>
            <state>C1</state>
            <symbol>0</symbol>
        </initcondition>
        <action>
            <state>C1</state>
            <symbol>0</symbol>
            <move>LEFT</move>
        </action>
    </rule>
    <rule>
        <initcondition>
            <state>C1</state>
            <symbol>1</symbol>
        </initcondition>
        <action>
            <state>C1</state>
            <symbol>1</symbol>
            <move>LEFT</move>
        </action>
    </rule>
    <rule>
        <initcondition>
            <state>F</state>
            <symbol>L</symbol>
        </initcondition>
        <action>
            <state>E</state>
            <symbol>L</symbol>
            <move>LEFT</move>
        </action>
    </rule>
    <rule>
        <initcondition>
            <state>X5</state>
            <symbol>c</symbol>
        </initcondition>
        <action>
            <state>X6</state>
            <symbol>c</symbol>
            <move>RIGHT</move>
        </action>
    </rule>
    <rule>
        <initcondition>
            <state>I</state>
            <symbol>c</symbol>
        </initcondition>
        <action>
            <state>J</state>
            <symbol>C</symbol>
            <move>RIGHT</move>
        </action>
    </rule>
    <rule>
        <initcondition>
            <state>F</state>
            <symbol>c</symbol>
        </initcondition>
        <action>
            <state>G</state>
            <symbol>c</symbol>
            <move>LEFT</move>
        </action>
    </rule>
    <rule>
        <initcondition>
            <state>J</state>
            <symbol>R</symbol>
        </initcondition>
        <action>
            <state>J</state>
            <symbol>R</symbol>
            <move>RIGHT</move>
        </action>
    </rule>
    <rule>
        <initcondition>
            <state>SL</state>
            <symbol>c</symbol>
        </initcondition>
        <action>
            <state>SL</state>
            <symbol>c</symbol>
            <move>RIGHT</move>
        </action>
    </rule>
    <rule>
        <initcondition>
            <state>C0</state>
            <symbol>1</symbol>
        </initcondition>
        <action>
            <state>C0</state>
            <symbol>1</symbol>
            <move>LEFT</move>
        </action>
    </rule>
    <rule>
        <initcondition>
            <state>C0</state>
            <symbol>0</symbol>
        </initcondition>
        <action>
            <state>C0</state>
            <symbol>0</symbol>
            <move>LEFT</move>
        </action>
    </rule>
    <rule>
        <initcondition>
            <state>J</state>
            <symbol>O</symbol>
        </initcondition>
        <action>
            <state>KL</state>
            <symbol>1</symbol>
            <move>RIGHT</move>
        </action>
    </rule>
    <rule>
        <initcondition>
            <state>D0</state>
            <symbol>1</symbol>
        </initcondition>
        <action>
            <state>D0</state>
            <symbol>1</symbol>
            <move>RIGHT</move>
        </action>
    </rule>
    <rule>
        <initcondition>
            <state>DB</state>
            <symbol>0</symbol>
        </initcondition>
        <action>
            <state>V</state>
            <symbol>0</symbol>
            <move>LEFT</move>
        </action>
    </rule>
    <rule>
        <initcondition>
            <state>DB</state>
            <symbol>1</symbol>
        </initcondition>
        <action>
            <state>E</state>
            <symbol>O</symbol>
            <move>LEFT</move>
        </action>
    </rule>
    <rule>
        <initcondition>
            <state>J</state>
            <symbol>L</symbol>
        </initcondition>
        <action>
            <state>J</state>
            <symbol>L</symbol>
            <move>RIGHT</move>
        </action>
    </rule>
    <rule>
        <initcondition>
            <state>X1</state>
            <symbol>c</symbol>
        </initcondition>
        <action>
            <state>X2</state>
            <symbol>c</symbol>
            <move>RIGHT</move>
        </action>
    </rule>
    <rule>
        <initcondition>
            <state>W</state>
            <symbol>R</symbol>
        </initcondition>
        <action>
            <state>V</state>
            <symbol>R</symbol>
            <move>LEFT</move>
        </action>
    </rule>
    <rule>
        <initcondition>
            <state>SL</state>
            <symbol>R</symbol>
        </initcondition>
        <action>
            <state>SL</state>
            <symbol>R</symbol>
            <move>RIGHT</move>
        </action>
    </rule>
    <rule>
        <initcondition>
            <state>SL</state>
            <symbol>O</symbol>
        </initcondition>
        <action>
            <state>KL</state>
            <symbol>1</symbol>
            <move>RIGHT</move>
        </action>
    </rule>
    <rule>
        <initcondition>
            <state>SL</state>
            <symbol>L</symbol>
        </initcondition>
        <action>
            <state>SL</state>
            <symbol>L</symbol>
            <move>RIGHT</move>
        </action>
    </rule>
    <rule>
        <initcondition>
            <state>TL0</state>
            <symbol>0</symbol>
        </initcondition>
        <action>
            <state>TL0</state>
            <symbol>0</symbol>
            <move>RIGHT</move>
        </action>
    </rule>
    <rule>
        <initcondition>
            <state>D0</state>
            <symbol>0</symbol>
        </initcondition>
        <action>
            <state>D0</state>
            <symbol>0</symbol>
            <move>RIGHT</move>
        </action>
    </rule>
    <rule>
        <initcondition>
            <state>NL</state>
            <symbol>c</symbol>
        </initcondition>
        <action>
            <state>PL</state>
            <symbol>c</symbol>
            <move>RIGHT</move>
        </action>
    </rule>
    <rule>
        <initcondition>
            <state>W</state>
            <symbol>L</symbol>
        </initcondition>
        <action>
            <state>V</state>
            <symbol>L</symbol>
            <move>LEFT</move>
        </action>
    </rule>
    <rule>
        <initcondition>
            <state>TL0</state>
            <symbol>1</symbol>
        </initcondition>
        <action>
            <state>TL0</state>
            <symbol>1</symbol>
            <move>RIGHT</move>
        </action>
    </rule>
    <rule>
        <initcondition>
            <state>TR0</state>
            <symbol>C</symbol>
        </initcondition>
        <action>
            <state>TR0</state>
            <symbol>C</symbol>
            <move>RIGHT</move>
        </action>
    </rule>
    <rule>
        <initcondition>
            <state>C0</state>
            <symbol>R</symbol>
        </initcondition>
        <action>
            <state>C0</state>
            <symbol>R</symbol>
            <move>LEFT</move>
        </action>
    </rule>
    <rule>
        <initcondition>
            <state>G</state>
            <symbol>0</symbol>
        </initcondition>
        <action>
            <state>E</state>
            <symbol>0</symbol>
            <move>LEFT</move>
        </action>
    </rule>
    <rule>
        <initcondition>
            <state>TL0</state>
            <symbol>C</symbol>
        </initcondition>
        <action>
            <state>TL0</state>
            <symbol>C</symbol>
            <move>RIGHT</move>
        </action>
    </rule>
    <rule>
        <initcondition>
            <state>C0</state>
            <symbol>L</symbol>
        </initcondition>
        <action>
            <state>C0</state>
            <symbol>L</symbol>
            <move>LEFT</move>
        </action>
    </rule>
    <rule>
        <initcondition>
            <state>G</state>
            <symbol>1</symbol>
        </initcondition>
        <action>
            <state>E</state>
            <symbol>1</symbol>
            <move>LEFT</move>
        </action>
    </rule>
    <rule>
        <initcondition>
            <state>J</state>
            <symbol>c</symbol>
        </initcondition>
        <action>
            <state>J</state>
            <symbol>c</symbol>
            <move>RIGHT</move>
        </action>
    </rule>
    <rule>
        <initcondition>
            <state>TL0</state>
            <symbol>B</symbol>
        </initcondition>
        <action>
            <state>U</state>
            <symbol>0</symbol>
            <move>LEFT</move>
        </action>
    </rule>
    <rule>
        <initcondition>
            <state>TR0</state>
            <symbol>B</symbol>
        </initcondition>
        <action>
            <state>U</state>
            <symbol>0</symbol>
            <move>RIGHT</move>
        </action>
    </rule>
    <rule>
        <initcondition>
            <state>SL</state>
            <symbol>0</symbol>
        </initcondition>
        <action>
            <state>SL</state>
            <symbol>0</symbol>
            <move>RIGHT</move>
        </action>
    </rule>
    <rule>
        <initcondition>
            <state>G</state>
            <symbol>L</symbol>
        </initcondition>
        <action>
            <state>E</state>
            <symbol>L</symbol>
            <move>LEFT</move>
        </action>
    </rule>
    <rule>
        <initcondition>
            <state>SL</state>
            <symbol>1</symbol>
        </initcondition>
        <action>
            <state>SL</state>
            <symbol>1</symbol>
            <move>RIGHT</move>
        </action>
    </rule>
    <rule>
        <initcondition>
            <state>C0</state>
            <symbol>C</symbol>
        </initcondition>
        <action>
            <state>D0</state>
            <symbol>c</symbol>
            <move>RIGHT</move>
        </action>
    </rule>
    <rule>
        <initcondition>
            <state>W</state>
            <symbol>c</symbol>
        </initcondition>
        <action>
            <state>X1</state>
            <symbol>c</symbol>
            <move>RIGHT</move>
        </action>
    </rule>
    <rule>
        <initcondition>
            <state>TL0</state>
            <symbol>L</symbol>
        </initcondition>
        <action>
            <state>TL0</state>
            <symbol>L</symbol>
            <move>RIGHT</move>
        </action>
    </rule>
    <rule>
        <initcondition>
            <state>TL0</state>
            <symbol>O</symbol>
        </initcondition>
        <action>
            <state>U</state>
            <symbol>0</symbol>
            <move>LEFT</move>
        </action>
    </rule>
    <rule>
        <initcondition>
            <state>TL0</state>
            <symbol>N</symbol>
        </initcondition>
        <action>
            <state>U</state>
            <symbol>0</symbol>
            <move>LEFT</move>
        </action>
    </rule>
    <rule>
        <initcondition>
            <state>TR0</state>
            <symbol>0</symbol>
        </initcondition>
        <action>
            <state>TR0</state>
            <symbol>0</symbol>
            <move>RIGHT</move>
        </action>
    </rule>
    <rule>
        <initcondition>
            <state>TR0</state>
            <symbol>1</symbol>
        </initcondition>
        <action>
            <state>TR0</state>
            <symbol>1</symbol>
            <move>RIGHT</move>
        </action>
    </rule>
    <rule>
        <initcondition>
            <state>TL0</state>
            <symbol>R</symbol>
        </initcondition>
        <action>
            <state>TL0</state>
            <symbol>R</symbol>
            <move>RIGHT</move>
        </action>
    </rule>
    <rule>
        <initcondition>
            <state>D1</state>
            <symbol>0</symbol>
        </initcondition>
        <action>
            <state>D1</state>
            <symbol>0</symbol>
            <move>RIGHT</move>
        </action>
    </rule>
    <rule>
        <initcondition>
            <state>D1</state>
            <symbol>1</symbol>
        </initcondition>
        <action>
            <state>D1</state>
            <symbol>1</symbol>
            <move>RIGHT</move>
        </action>
    </rule>
    <rule>
        <initcondition>
            <state>V</state>
            <symbol>c</symbol>
        </initcondition>
        <action>
            <state>W</state>
            <symbol>c</symbol>
            <move>LEFT</move>
        </action>
    </rule>
    <rule>
        <initcondition>
            <state>SR</state>
            <symbol>c</symbol>
        </initcondition>
        <action>
            <state>SR</state>
            <symbol>c</symbol>
            <move>LEFT</move>
        </action>
    </rule>
    <rule>
        <initcondition>
            <state>G</state>
            <symbol>c</symbol>
        </initcondition>
        <action>
            <state>H</state>
            <symbol>c</symbol>
            <move>RIGHT</move>
        </action>
    </rule>
    <rule>
        <initcondition>
            <state>MR</state>
            <symbol>1</symbol>
        </initcondition>
        <action>
            <state>MR</state>
            <symbol>1</symbol>
            <move>RIGHT</move>
        </action>
    </rule>
    <rule>
        <initcondition>
            <state>MR</state>
            <symbol>0</symbol>
        </initcondition>
        <action>
            <state>MR</state>
            <symbol>0</symbol>
            <move>RIGHT</move>
        </action>
    </rule>
    <rule>
        <initcondition>
            <state>A</state>
            <symbol>C</symbol>
        </initcondition>
        <action>
            <state>B</state>
            <symbol>C</symbol>
            <move>RIGHT</move>
        </action>
    </rule>
    <rule>
        <initcondition>
            <state>NL</state>
            <symbol>L</symbol>
        </initcondition>
        <action>
            <state>NL</state>
            <symbol>L</symbol>
            <move>RIGHT</move>
        </action>
    </rule>
    <rule>
        <initcondition>
            <state>V</state>
            <symbol>R</symbol>
        </initcondition>
        <action>
            <state>V</state>
            <symbol>R</symbol>
            <move>LEFT</move>
        </action>
    </rule>
    <rule>
        <initcondition>
            <state>NL</state>
            <symbol>R</symbol>
        </initcondition>
        <action>
            <state>NL</state>
            <symbol>R</symbol>
            <move>RIGHT</move>
        </action>
    </rule>
    <rule>
        <initcondition>
            <state>G</state>
            <symbol>R</symbol>
        </initcondition>
        <action>
            <state>E</state>
            <symbol>R</symbol>
            <move>LEFT</move>
        </action>
    </rule>
    <rule>
        <initcondition>
            <state>NL</state>
            <symbol>O</symbol>
        </initcondition>
        <action>
            <state>NR</state>
            <symbol>O</symbol>
            <move>RIGHT</move>
        </action>
    </rule>
    <rule>
        <initcondition>
            <state>A</state>
            <symbol>1</symbol>
        </initcondition>
        <action>
            <state>A</state>
            <symbol>1</symbol>
            <move>RIGHT</move>
        </action>
    </rule>
    <rule>
        <initcondition>
            <state>CB</state>
            <symbol>c</symbol>
        </initcondition>
        <action>
            <state>CB</state>
            <symbol>c</symbol>
            <move>LEFT</move>
        </action>
    </rule>
    <rule>
        <initcondition>
            <state>A</state>
            <symbol>0</symbol>
        </initcondition>
        <action>
            <state>A</state>
            <symbol>0</symbol>
            <move>RIGHT</move>
        </action>
    </rule>
    <rule>
        <initcondition>
            <state>V</state>
            <symbol>L</symbol>
        </initcondition>
        <action>
            <state>V</state>
            <symbol>L</symbol>
            <move>LEFT</move>
        </action>
    </rule>
    <rule>
        <initcondition>
            <state>D0</state>
            <symbol>c</symbol>
        </initcondition>
        <action>
            <state>DB</state>
            <symbol>c</symbol>
            <move>RIGHT</move>
        </action>
    </rule>
    <rule>
        <initcondition>
            <state>CB</state>
            <symbol>L</symbol>
        </initcondition>
        <action>
            <state>CB</state>
            <symbol>L</symbol>
            <move>LEFT</move>
        </action>
    </rule>
    <rule>
        <initcondition>
            <state>X3</state>
            <symbol>c</symbol>
        </initcondition>
        <action>
            <state>X4</state>
            <symbol>c</symbol>
            <move>RIGHT</move>
        </action>
    </rule>
    <rule>
        <initcondition>
            <state>PR</state>
            <symbol>1</symbol>
        </initcondition>
        <action>
            <state>NR</state>
            <symbol>1</symbol>
            <move>RIGHT</move>
        </action>
    </rule>
    <rule>
        <initcondition>
            <state>PR</state>
            <symbol>0</symbol>
        </initcondition>
        <action>
            <state>NR</state>
            <symbol>0</symbol>
            <move>RIGHT</move>
        </action>
    </rule>
    <rule>
        <initcondition>
            <state>CB</state>
            <symbol>R</symbol>
        </initcondition>
        <action>
            <state>CB</state>
            <symbol>R</symbol>
            <move>LEFT</move>
        </action>
    </rule>
    <rule>
        <initcondition>
            <state>D0</state>
            <symbol>R</symbol>
        </initcondition>
        <action>
            <state>D0</state>
            <symbol>R</symbol>
            <move>RIGHT</move>
        </action>
    </rule>
    <rule>
        <initcondition>
            <state>W</state>
            <symbol>0</symbol>
        </initcondition>
        <action>
            <state>V</state>
            <symbol>0</symbol>
            <move>LEFT</move>
        </action>
    </rule>
    <rule>
        <initcondition>
            <state>W</state>
            <symbol>1</symbol>
        </initcondition>
        <action>
            <state>V</state>
            <symbol>1</symbol>
            <move>LEFT</move>
        </action>
    </rule>
    <rule>
        <initcondition>
            <state>D0</state>
            <symbol>L</symbol>
        </initcondition>
        <action>
            <state>D0</state>
            <symbol>L</symbol>
            <move>RIGHT</move>
        </action>
    </rule>
    <rule>
        <initcondition>
            <state>X4</state>
            <symbol>0</symbol>
        </initcondition>
        <action>
            <state>X5</state>
            <symbol>0</symbol>
            <move>RIGHT</move>
        </action>
    </rule>
    <rule>
        <initcondition>
            <state>SR</state>
            <symbol>O</symbol>
        </initcondition>
        <action>
            <state>KR</state>
            <symbol>1</symbol>
            <move>RIGHT</move>
        </action>
    </rule>
    <rule>
        <initcondition>
            <state>NL</state>
            <symbol>0</symbol>
        </initcondition>
        <action>
            <state>NL</state>
            <symbol>0</symbol>
            <move>RIGHT</move>
        </action>
    </rule>
    <rule>
        <initcondition>
            <state>SR</state>
            <symbol>R</symbol>
        </initcondition>
        <action>
            <state>SR</state>
            <symbol>R</symbol>
            <move>LEFT</move>
        </action>
    </rule>
    <rule>
        <initcondition>
            <state>NL</state>
            <symbol>1</symbol>
        </initcondition>
        <action>
            <state>NL</state>
            <symbol>1</symbol>
            <move>RIGHT</move>
        </action>
    </rule>
    <rule>
        <initcondition>
            <state>CB</state>
            <symbol>C</symbol>
        </initcondition>
        <action>
            <state>DB</state>
            <symbol>c</symbol>
            <move>RIGHT</move>
        </action>
    </rule>
    <rule>
        <initcondition>
            <state>SR</state>
            <symbol>L</symbol>
        </initcondition>
        <action>
            <state>SR</state>
            <symbol>L</symbol>
            <move>LEFT</move>
        </action>
    </rule>
    <rule>
        <initcondition>
            <state>PR</state>
            <symbol>R</symbol>
        </initcondition>
        <action>
            <state>NR</state>
            <symbol>R</symbol>
            <move>RIGHT</move>
        </action>
    </rule>
    <rule>
        <initcondition>
            <state>C1</state>
            <symbol>R</symbol>
        </initcondition>
        <action>
            <state>C1</state>
            <symbol>R</symbol>
            <move>LEFT</move>
        </action>
    </rule>
    <rule>
        <initcondition>
            <state>TR1</state>
            <symbol>R</symbol>
        </initcondition>
        <action>
            <state>TR1</state>
            <symbol>R</symbol>
            <move>RIGHT</move>
        </action>
    </rule>
    <rule>
        <initcondition>
            <state>NR</state>
            <symbol>0</symbol>
        </initcondition>
        <action>
            <state>NR</state>
            <symbol>0</symbol>
            <move>RIGHT</move>
        </action>
    </rule>
    <rule>
        <initcondition>
            <state>PR</state>
            <symbol>L</symbol>
        </initcondition>
        <action>
            <state>NR</state>
            <symbol>L</symbol>
            <move>RIGHT</move>
        </action>
    </rule>
    <rule>
        <initcondition>
            <state>B</state>
            <symbol>0</symbol>
        </initcondition>
        <action>
            <state>B</state>
            <symbol>0</symbol>
            <move>RIGHT</move>
        </action>
    </rule>
    <rule>
        <initcondition>
            <state>B</state>
            <symbol>1</symbol>
        </initcondition>
        <action>
            <state>B</state>
            <symbol>1</symbol>
            <move>RIGHT</move>
        </action>
    </rule>
    <rule>
        <initcondition>
            <state>PL</state>
            <symbol>R</symbol>
        </initcondition>
        <action>
            <state>NL</state>
            <symbol>R</symbol>
            <move>RIGHT</move>
        </action>
    </rule>
    <rule>
        <initcondition>
            <state>U</state>
            <symbol>b</symbol>
        </initcondition>
        <action>
            <state>CB</state>
            <symbol>B</symbol>
            <move>LEFT</move>
        </action>
    </rule>
    <rule>
        <initcondition>
            <state>TL1</state>
            <symbol>L</symbol>
        </initcondition>
        <action>
            <state>TL1</state>
            <symbol>L</symbol>
            <move>RIGHT</move>
        </action>
    </rule>
    <rule>
        <initcondition>
            <state>H</state>
            <symbol>c</symbol>
        </initcondition>
        <action>
            <state>I</state>
            <symbol>c</symbol>
            <move>RIGHT</move>
        </action>
    </rule>
    <rule>
        <initcondition>
            <state>TL1</state>
            <symbol>N</symbol>
        </initcondition>
        <action>
            <state>U</state>
            <symbol>1</symbol>
            <move>LEFT</move>
        </action>
    </rule>
    <rule>
        <initcondition>
            <state>CB</state>
            <symbol>0</symbol>
        </initcondition>
        <action>
            <state>CB</state>
            <symbol>0</symbol>
            <move>LEFT</move>
        </action>
    </rule>
    <rule>
        <initcondition>
            <state>TL1</state>
            <symbol>O</symbol>
        </initcondition>
        <action>
            <state>U</state>
            <symbol>1</symbol>
            <move>LEFT</move>
        </action>
    </rule>
    <rule>
        <initcondition>
            <state>CB</state>
            <symbol>1</symbol>
        </initcondition>
        <action>
            <state>CB</state>
            <symbol>1</symbol>
            <move>LEFT</move>
        </action>
    </rule>
    <rule>
        <initcondition>
            <state>NR</state>
            <symbol>1</symbol>
        </initcondition>
        <action>
            <state>NR</state>
            <symbol>1</symbol>
            <move>RIGHT</move>
        </action>
    </rule>
    <rule>
        <initcondition>
            <state>TL1</state>
            <symbol>R</symbol>
        </initcondition>
        <action>
            <state>TL1</state>
            <symbol>R</symbol>
            <move>RIGHT</move>
        </action>
    </rule>
    <rule>
        <initcondition>
            <state>TR1</state>
            <symbol>B</symbol>
        </initcondition>
        <action>
            <state>U</state>
            <symbol>1</symbol>
            <move>RIGHT</move>
        </action>
    </rule>
    <rule>
        <initcondition>
            <state>TR1</state>
            <symbol>C</symbol>
        </initcondition>
        <action>
            <state>TR1</state>
            <symbol>C</symbol>
            <move>RIGHT</move>
        </action>
    </rule>
    <rule>
        <initcondition>
            <state>E</state>
            <symbol>0</symbol>
        </initcondition>
        <action>
            <state>E</state>
            <symbol>0</symbol>
            <move>LEFT</move>
        </action>
    </rule>
    <rule>
        <initcondition>
            <state>C1</state>
            <symbol>c</symbol>
        </initcondition>
        <action>
            <state>C1</state>
            <symbol>c</symbol>
            <move>LEFT</move>
        </action>
    </rule>
    <rule>
        <initcondition>
            <state>PL</state>
            <symbol>c</symbol>
        </initcondition>
        <action>
            <state>SL</state>
            <symbol>C</symbol>
            <move>RIGHT</move>
        </action>
    </rule>
    <rule>
        <initcondition>
            <state>E</state>
            <symbol>1</symbol>
        </initcondition>
        <action>
            <state>E</state>
            <symbol>1</symbol>
            <move>LEFT</move>
        </action>
    </rule>
    <rule>
        <initcondition>
            <state>SR</state>
            <symbol>0</symbol>
        </initcondition>
        <action>
            <state>SR</state>
            <symbol>0</symbol>
            <move>LEFT</move>
        </action>
    </rule>
    <rule>
        <initcondition>
            <state>D1</state>
            <symbol>c</symbol>
        </initcondition>
        <action>
            <state>D0</state>
            <symbol>c</symbol>
            <move>RIGHT</move>
        </action>
    </rule>
    <rule>
        <initcondition>
            <state>SR</state>
            <symbol>1</symbol>
        </initcondition>
        <action>
            <state>SR</state>
            <symbol>1</symbol>
            <move>LEFT</move>
        </action>
    </rule>
    <rule>
        <initcondition>
            <state>TR1</state>
            <symbol>L</symbol>
        </initcondition>
        <action>
            <state>TR1</state>
            <symbol>L</symbol>
            <move>RIGHT</move>
        </action>
    </rule>
    <rule>
        <initcondition>
            <state>MR</state>
            <symbol>c</symbol>
        </initcondition>
        <action>
            <state>MR</state>
            <symbol>c</symbol>
            <move>RIGHT</move>
        </action>
    </rule>
    <rule>
        <initcondition>
            <state>TR1</state>
            <symbol>N</symbol>
        </initcondition>
        <action>
            <state>U</state>
            <symbol>1</symbol>
            <move>RIGHT</move>
        </action>
    </rule>
    <rule>
        <initcondition>
            <state>TL1</state>
            <symbol>c</symbol>
        </initcondition>
        <action>
            <state>TL1</state>
            <symbol>c</symbol>
            <move>RIGHT</move>
        </action>
    </rule>
    <rule>
        <initcondition>
            <state>TR1</state>
            <symbol>O</symbol>
        </initcondition>
        <action>
            <state>U</state>
            <symbol>1</symbol>
            <move>RIGHT</move>
        </action>
    </rule>
    <rule>
        <initcondition>
            <state>ML</state>
            <symbol>1</symbol>
        </initcondition>
        <action>
            <state>ML</state>
            <symbol>1</symbol>
            <move>LEFT</move>
        </action>
    </rule>
    <rule>
        <initcondition>
            <state>ML</state>
            <symbol>0</symbol>
        </initcondition>
        <action>
            <state>ML</state>
            <symbol>0</symbol>
            <move>LEFT</move>
        </action>
    </rule>
    <rule>
        <initcondition>
            <state>D1</state>
            <symbol>R</symbol>
        </initcondition>
        <action>
            <state>D1</state>
            <symbol>R</symbol>
            <move>RIGHT</move>
        </action>
    </rule>
    <rule>
        <initcondition>
            <state>NR</state>
            <symbol>L</symbol>
        </initcondition>
        <action>
            <state>NR</state>
            <symbol>L</symbol>
            <move>RIGHT</move>
        </action>
    </rule>
    <rule>
        <initcondition>
            <state>PL</state>
            <symbol>1</symbol>
        </initcondition>
        <action>
            <state>NL</state>
            <symbol>1</symbol>
            <move>RIGHT</move>
        </action>
    </rule>
    <rule>
        <initcondition>
            <state>D1</state>
            <symbol>L</symbol>
        </initcondition>
        <action>
            <state>D1</state>
            <symbol>L</symbol>
            <move>RIGHT</move>
        </action>
    </rule>
    <rule>
        <initcondition>
            <state>E</state>
            <symbol>L</symbol>
        </initcondition>
        <action>
            <state>E</state>
            <symbol>L</symbol>
            <move>LEFT</move>
        </action>
    </rule>
    <rule>
        <initcondition>
            <state>A</state>
            <symbol>c</symbol>
        </initcondition>
        <action>
            <state>A</state>
            <symbol>c</symbol>
            <move>RIGHT</move>
        </action>
    </rule>
    <rule>
        <initcondition>
            <state>NR</state>
            <symbol>R</symbol>
        </initcondition>
        <action>
            <state>NR</state>
            <symbol>R</symbol>
            <move>RIGHT</move>
        </action>
    </rule>
    <rule>
        <initcondition>
            <state>MR</state>
            <symbol>R</symbol>
        </initcondition>
        <action>
            <state>MR</state>
            <symbol>R</symbol>
            <move>RIGHT</move>
        </action>
    </rule>
    <rule>
        <initcondition>
            <state>V</state>
            <symbol>0</symbol>
        </initcondition>
        <action>
            <state>V</state>
            <symbol>0</symbol>
            <move>LEFT</move>
        </action>
    </rule>
    <rule>
        <initcondition>
            <state>MR</state>
            <symbol>L</symbol>
        </initcondition>
        <action>
            <state>MR</state>
            <symbol>L</symbol>
            <move>RIGHT</move>
        </action>
    </rule>
    <rule>
        <initcondition>
            <state>TR1</state>
            <symbol>c</symbol>
        </initcondition>
        <action>
            <state>TR1</state>
            <symbol>c</symbol>
            <move>RIGHT</move>
        </action>
    </rule>
    <rule>
        <initcondition>
            <state>V</state>
            <symbol>1</symbol>
        </initcondition>
        <action>
            <state>V</state>
            <symbol>1</symbol>
            <move>LEFT</move>
        </action>
    </rule>
    <rule>
        <initcondition>
            <state>E</state>
            <symbol>R</symbol>
        </initcondition>
        <action>
            <state>E</state>
            <symbol>R</symbol>
            <move>LEFT</move>
        </action>
    </rule>
    <rule>
        <initcondition>
            <state>PL</state>
            <symbol>O</symbol>
        </initcondition>
        <action>
            <state>NR</state>
            <symbol>O</symbol>
            <move>RIGHT</move>
        </action>
    </rule>
    <rule>
        <initcondition>
            <state>A</state>
            <symbol>L</symbol>
        </initcondition>
        <action>
            <state>A</state>
            <symbol>L</symbol>
            <move>RIGHT</move>
        </action>
    </rule>
    <rule>
        <initcondition>
            <state>NR</state>
            <symbol>c</symbol>
        </initcondition>
        <action>
            <state>PR</state>
            <symbol>c</symbol>
            <move>RIGHT</move>
        </action>
    </rule>
    <rule>
        <initcondition>
            <state>A</state>
            <symbol>R</symbol>
        </initcondition>
        <action>
            <state>A</state>
            <symbol>R</symbol>
            <move>RIGHT</move>
        </action>
    </rule>
    <rule>
        <initcondition>
            <state>PR</state>
            <symbol>c</symbol>
        </initcondition>
        <action>
            <state>SR</state>
            <symbol>C</symbol>
            <move>LEFT</move>
        </action>
    </rule>
    <rule>
        <initcondition>
            <state>MR</state>
            <symbol>C</symbol>
        </initcondition>
        <action>
            <state>NR</state>
            <symbol>c</symbol>
            <move>RIGHT</move>
        </action>
    </rule>
    <rule>
        <initcondition>
            <state>PL</state>
            <symbol>L</symbol>
        </initcondition>
        <action>
            <state>NL</state>
            <symbol>L</symbol>
            <move>RIGHT</move>
        </action>
    </rule>
</program>
