<?xml version="1.0" encoding="Windows-1251"?>
<reg>
    <regexp>
        <value>a*</value>
        <test1>aaaaaaaaaaaaaaaaaaaaaaaaaa</test1>
        <test2>aaaaaaaaaaaaaaaaaaaaaaaaaa</test2>
        <test3>aaaaaaaaaaaaaaaaaaaaaaaaaa</test3>
        <test4>
            <len>10</len>
            <num>10000</num>
        </test4>
    </regexp>
    <regexp>
        <value>(asdfgh)*|(asdfghj)*</value>
        <test1>asdfghjasdfghjasdfghj</test1>
        <test2>asdfghasdfghasdfghasdfghs</test2>
        <test3>asdfghjasdfghjasdfghjasdfghj</test3>
        <test4>
            <len>12</len>
            <num>10000</num>
        </test4>
    </regexp>
    <regexp>
        <value>a*b*c*d*</value>
        <test1>abbccddddd</test1>
        <test2>abbbbbbbbcbbbccccccdddddd</test2>
        <test3>aaabbbccccddd</test3>
        <test4>
            <len>10</len>
            <num>10000</num>
        </test4>
    </regexp>
    <regexp>
        <value>(qwer)*|qerty|(qwe)*</value>
        <test1>qweqweqweqweqweqweqweqweqwe</test1>
        <test2>qweqweqweqweqweqwert</test2>
        <test3>qweqweqweqweqweqwerty</test3>
        <test4>
            <len>9</len>
            <num>1000000</num>
        </test4>
    </regexp>
    <regexp>
        <value>a(s|d)*fg(hj*|hk)*</value>
        <test1>asssdddfghjhkhjjjhkhkhk</test1>
        <test2>assdddfghkhkhkhjhjhjhjhjhkhjhkhjhkj</test2>
        <test3>asdsdsdsdsdfghkhkhkhjjjjjjhkhk</test3>
        <test4>
            <len>5</len>
            <num>1000000</num>
        </test4>
    </regexp>
</reg>
